yuko-0.1.0.dist-info/METADATA
yuko-0.1.0.dist-info/WHEEL
yuko-0.1.0.dist-info/license_files/LICENSE
yuko/yuko.pyi
yuko/__init__.py
yuko/py.typed
yuko/yuko.cpython-312-i386-linux-gnu.so
yuko-0.1.0.dist-info/RECORD
